<mxGraphModel><root><mxCell id="0"/><mxCell id="1" parent="0"/><mxCell id="30" style="entity" parent="1" vertex="1" connectable="0"><ErEntity name="Kniha" as="value"><ErEntityGBHandler as="erGraphBehaviourHandler"/></ErEntity><mxGeometry x="743" y="188" width="100" height="40" as="geometry"/></mxCell><mxCell id="31" style="attribute;attributeLabelTop" parent="1" vertex="1" connectable="0"><ErAttribute name="nazev" as="value"><ErAttributeGBHandler as="erGraphBehaviourHandler"/></ErAttribute><mxGeometry x="906" y="75" width="13" height="13" as="geometry"/></mxCell><mxCell id="32" style="attributeConnector" parent="1" source="31" target="30" edge="1"><ErAttributeConnector as="value"><ErAttributeConnectorGBHandler as="erGraphBehaviourHandler"/></ErAttributeConnector><mxGeometry relative="1" as="geometry"/></mxCell><mxCell id="35" style="attribute;attributeIdentifier;attributeLabelTop" parent="1" vertex="1" connectable="0"><ErAttribute name="ISBN" simpleIdentifier="1" as="value"><ErAttributeGBHandler as="erGraphBehaviourHandler"/></ErAttribute><mxGeometry x="819" y="114" width="13" height="13" as="geometry"/></mxCell><mxCell id="36" style="attributeConnector" parent="1" source="35" target="30" edge="1"><ErAttributeConnector as="value"><ErAttributeConnectorGBHandler as="erGraphBehaviourHandler"/></ErAttributeConnector><mxGeometry relative="1" as="geometry"/></mxCell><mxCell id="37" style="attribute;attributeLabelTop" parent="1" vertex="1" connectable="0"><ErAttribute name="vydavatel" as="value"><ErAttributeGBHandler as="erGraphBehaviourHandler"/></ErAttribute><mxGeometry x="900.5" y="118" width="13" height="13" as="geometry"/></mxCell><mxCell id="38" style="attributeConnector" parent="1" source="37" target="30" edge="1"><ErAttributeConnector as="value"><ErAttributeConnectorGBHandler as="erGraphBehaviourHandler"/></ErAttributeConnector><mxGeometry relative="1" as="geometry"/></mxCell><mxCell id="39" style="attribute;attributeLabelTop" parent="1" vertex="1" connectable="0"><ErAttribute name="autor" multivalued="1" cardinalityMin="1" cardinalityMax="N" as="value"><ErAttributeGBHandler as="erGraphBehaviourHandler"/></ErAttribute><mxGeometry x="697" y="148" width="13" height="13" as="geometry"/></mxCell><mxCell id="40" style="attributeConnector" parent="1" source="39" target="30" edge="1"><ErAttributeConnector as="value"><ErAttributeConnectorGBHandler as="erGraphBehaviourHandler"/></ErAttributeConnector><mxGeometry relative="1" as="geometry"/></mxCell><mxCell id="41" style="attribute;attributeLabelTop" parent="1" vertex="1" connectable="0"><ErAttribute name="rok vydani" as="value"><ErAttributeGBHandler as="erGraphBehaviourHandler"/></ErAttribute><mxGeometry x="951" y="108" width="13" height="13" as="geometry"/></mxCell><mxCell id="42" style="attributeConnector" parent="1" source="41" target="30" edge="1"><ErAttributeConnector as="value"><ErAttributeConnectorGBHandler as="erGraphBehaviourHandler"/></ErAttributeConnector><mxGeometry relative="1" as="geometry"/></mxCell><mxCell id="43" style="attribute;attributeLabelTop" parent="1" vertex="1" connectable="0"><ErAttribute name="anotace" multivalued="1" cardinalityMin="0" cardinalityMax="1" as="value"><ErAttributeGBHandler as="erGraphBehaviourHandler"/></ErAttribute><mxGeometry x="638" y="154" width="13" height="13" as="geometry"/></mxCell><mxCell id="44" style="attributeConnector" parent="1" source="43" target="30" edge="1"><ErAttributeConnector as="value"><ErAttributeConnectorGBHandler as="erGraphBehaviourHandler"/></ErAttributeConnector><mxGeometry relative="1" as="geometry"/></mxCell><mxCell id="67" style="compositeIdentifier" parent="1" vertex="1" connectable="0"><ErCompositeIdentifier as="value"><ErCompositeIdentifierGBHandler as="erGraphBehaviourHandler"/></ErCompositeIdentifier><mxGeometry as="geometry"><mxPoint x="819.5650682685139" y="164" as="sourcePoint"/><mxPoint x="867" y="180.93346790134092" as="targetPoint"/><Array as="points"><mxPoint x="834.5650682685139" y="164"/><mxPoint x="843" y="164"/><mxPoint x="853.0537686456275" y="164"/><mxPoint x="867" y="164"/><mxPoint x="867" y="165.93346790134092"/></Array></mxGeometry></mxCell><mxCell id="68" parent="1" source="67" target="30" edge="1" visible="0"><ErCompositeIdentifierConnector as="value"><ErCompositeIdentifierConnectorGBHandler as="erGraphBehaviourHandler"/></ErCompositeIdentifierConnector><mxGeometry relative="1" as="geometry"/></mxCell><mxCell id="69" parent="1" source="67" target="38" edge="1" visible="0"><ErCompositeIdentifierMember as="value"><ErCompositeIdentifierMemberGBHandler as="erGraphBehaviourHandler"/></ErCompositeIdentifierMember><mxGeometry relative="1" as="geometry"/></mxCell><mxCell id="70" style="intersectionPoint" parent="1" vertex="1" connectable="0"><ErCompositeIdentifierIntersectionPoint as="value"><ErCompositeIdentifierIPointGBHandler as="erGraphBehaviourHandler"/></ErCompositeIdentifierIntersectionPoint><mxGeometry x="851.0537686456275" y="162" width="4" height="4" as="geometry"/></mxCell><mxCell id="71" parent="1" source="67" target="70" edge="1" visible="0"><ErCompositeIdentifierIntersectionPointConnector as="value"><ErCompositeIdentifierIPointConnectorGBHandler as="erGraphBehaviourHandler"/></ErCompositeIdentifierIntersectionPointConnector><mxGeometry relative="1" as="geometry"/></mxCell><mxCell id="72" parent="1" source="67" target="42" edge="1" visible="0"><ErCompositeIdentifierMember as="value"><ErCompositeIdentifierMemberGBHandler as="erGraphBehaviourHandler"/></ErCompositeIdentifierMember><mxGeometry relative="1" as="geometry"/></mxCell><mxCell id="73" style="intersectionPoint" parent="1" vertex="1" connectable="0"><ErCompositeIdentifierIntersectionPoint as="value"><ErCompositeIdentifierIPointGBHandler as="erGraphBehaviourHandler"/></ErCompositeIdentifierIntersectionPoint><mxGeometry x="865" y="163.93346790134092" width="4" height="4" as="geometry"/></mxCell><mxCell id="74" parent="1" source="67" target="73" edge="1" visible="0"><ErCompositeIdentifierIntersectionPointConnector as="value"><ErCompositeIdentifierIPointConnectorGBHandler as="erGraphBehaviourHandler"/></ErCompositeIdentifierIntersectionPointConnector><mxGeometry relative="1" as="geometry"/></mxCell><mxCell id="75" parent="1" source="67" target="32" edge="1" visible="0"><ErCompositeIdentifierMember as="value"><ErCompositeIdentifierMemberGBHandler as="erGraphBehaviourHandler"/></ErCompositeIdentifierMember><mxGeometry relative="1" as="geometry"/></mxCell><mxCell id="76" style="intersectionPoint" parent="1" vertex="1" connectable="0"><ErCompositeIdentifierIntersectionPoint as="value"><ErCompositeIdentifierIPointGBHandler as="erGraphBehaviourHandler"/></ErCompositeIdentifierIntersectionPoint><mxGeometry x="832.5650682685139" y="162" width="4" height="4" as="geometry"/></mxCell><mxCell id="77" parent="1" source="67" target="76" edge="1" visible="0"><ErCompositeIdentifierIntersectionPointConnector as="value"><ErCompositeIdentifierIPointConnectorGBHandler as="erGraphBehaviourHandler"/></ErCompositeIdentifierIntersectionPointConnector><mxGeometry relative="1" as="geometry"/></mxCell><mxCell id="78" style="entity" parent="1" vertex="1" connectable="0"><ErEntity name="Oficialni stranka" as="value"><ErEntityGBHandler as="erGraphBehaviourHandler"/></ErEntity><mxGeometry x="743" y="409" width="100" height="40" as="geometry"/></mxCell><mxCell id="79" style="entity" parent="1" vertex="1" connectable="0"><ErEntity name="Zanr" as="value"><ErEntityGBHandler as="erGraphBehaviourHandler"/></ErEntity><mxGeometry x="556" y="409" width="100" height="40" as="geometry"/></mxCell><mxCell id="80" style="entity" parent="1" vertex="1" connectable="0"><ErEntity name="Komentar" as="value"><ErEntityGBHandler as="erGraphBehaviourHandler"/></ErEntity><mxGeometry x="960" y="409" width="100" height="40" as="geometry"/></mxCell><mxCell id="81" style="attribute;attributeIdentifier;attributeLabelBottom" parent="1" vertex="1" connectable="0"><ErAttribute name="URL adresa" simpleIdentifier="1" as="value"><ErAttributeGBHandler as="erGraphBehaviourHandler"/></ErAttribute><mxGeometry x="773" y="478" width="13" height="13" as="geometry"/></mxCell><mxCell id="82" style="attributeConnector" parent="1" source="81" target="78" edge="1"><ErAttributeConnector as="value"><ErAttributeConnectorGBHandler as="erGraphBehaviourHandler"/></ErAttributeConnector><mxGeometry relative="1" as="geometry"/></mxCell><mxCell id="83" style="attribute;attributeLabelTop" parent="1" vertex="1" connectable="0"><ErAttribute name="nazev" as="value"><ErAttributeGBHandler as="erGraphBehaviourHandler"/></ErAttribute><mxGeometry x="1114" y="422.5" width="13" height="13" as="geometry"/></mxCell><mxCell id="84" style="attributeConnector" parent="1" source="83" target="80" edge="1"><ErAttributeConnector as="value"><ErAttributeConnectorGBHandler as="erGraphBehaviourHandler"/></ErAttributeConnector><mxGeometry relative="1" as="geometry"/></mxCell><mxCell id="85" style="attribute;attributeLabelBottom" parent="1" vertex="1" connectable="0"><ErAttribute name="datum vydani" as="value"><ErAttributeGBHandler as="erGraphBehaviourHandler"/></ErAttribute><mxGeometry x="1114" y="449" width="13" height="13" as="geometry"/></mxCell><mxCell id="86" style="attributeConnector" parent="1" source="85" target="80" edge="1"><ErAttributeConnector as="value"><ErAttributeConnectorGBHandler as="erGraphBehaviourHandler"/></ErAttributeConnector><mxGeometry relative="1" as="geometry"/></mxCell><mxCell id="87" style="attribute;attributeIdentifier;attributeLabelBottom" parent="1" vertex="1" connectable="0"><ErAttribute name="nazev" simpleIdentifier="1" as="value"><ErAttributeGBHandler as="erGraphBehaviourHandler"/></ErAttribute><mxGeometry x="682" y="445.52" width="13" height="13" as="geometry"/></mxCell><mxCell id="88" style="attributeConnector" parent="1" source="87" target="79" edge="1"><ErAttributeConnector as="value"><ErAttributeConnectorGBHandler as="erGraphBehaviourHandler"/></ErAttributeConnector><mxGeometry relative="1" as="geometry"/></mxCell><mxCell id="89" style="compositeIdentifier" parent="1" vertex="1" connectable="0"><ErCompositeIdentifier as="value"><ErCompositeIdentifierGBHandler as="erGraphBehaviourHandler"/></ErCompositeIdentifier><mxGeometry as="geometry"><mxPoint x="1084.0000000000002" y="413.9468428113125" as="sourcePoint"/><mxPoint x="1084.0000000000002" y="461.7913118876915" as="targetPoint"/><Array as="points"><mxPoint x="1084.0000000000002" y="428.9468428113125"/><mxPoint x="1084.0000000000002" y="446.7913118876915"/></Array></mxGeometry></mxCell><mxCell id="90" parent="1" source="89" target="80" edge="1" visible="0"><ErCompositeIdentifierConnector as="value"><ErCompositeIdentifierConnectorGBHandler as="erGraphBehaviourHandler"/></ErCompositeIdentifierConnector><mxGeometry relative="1" as="geometry"/></mxCell><mxCell id="91" parent="1" source="89" target="84" edge="1" visible="0"><ErCompositeIdentifierMember as="value"><ErCompositeIdentifierMemberGBHandler as="erGraphBehaviourHandler"/></ErCompositeIdentifierMember><mxGeometry relative="1" as="geometry"/></mxCell><mxCell id="92" style="intersectionPoint" parent="1" vertex="1" connectable="0"><ErCompositeIdentifierIntersectionPoint as="value"><ErCompositeIdentifierIPointGBHandler as="erGraphBehaviourHandler"/></ErCompositeIdentifierIntersectionPoint><mxGeometry x="1082.0000000000002" y="426.9468428113125" width="4" height="4" as="geometry"/></mxCell><mxCell id="93" parent="1" source="89" target="92" edge="1" visible="0"><ErCompositeIdentifierIntersectionPointConnector as="value"><ErCompositeIdentifierIPointConnectorGBHandler as="erGraphBehaviourHandler"/></ErCompositeIdentifierIntersectionPointConnector><mxGeometry relative="1" as="geometry"/></mxCell><mxCell id="94" parent="1" source="89" target="86" edge="1" visible="0"><ErCompositeIdentifierMember as="value"><ErCompositeIdentifierMemberGBHandler as="erGraphBehaviourHandler"/></ErCompositeIdentifierMember><mxGeometry relative="1" as="geometry"/></mxCell><mxCell id="95" style="intersectionPoint" parent="1" vertex="1" connectable="0"><ErCompositeIdentifierIntersectionPoint as="value"><ErCompositeIdentifierIPointGBHandler as="erGraphBehaviourHandler"/></ErCompositeIdentifierIntersectionPoint><mxGeometry x="1082.0000000000002" y="444.7913118876915" width="4" height="4" as="geometry"/></mxCell><mxCell id="96" parent="1" source="89" target="95" edge="1" visible="0"><ErCompositeIdentifierIntersectionPointConnector as="value"><ErCompositeIdentifierIPointConnectorGBHandler as="erGraphBehaviourHandler"/></ErCompositeIdentifierIntersectionPointConnector><mxGeometry relative="1" as="geometry"/></mxCell><mxCell id="97" style="relationship" parent="1" vertex="1"><ErRelationship name="popisuje" as="value"><ErRelationshipGBHandler as="erGraphBehaviourHandler"/></ErRelationship><mxGeometry x="743" y="266" width="100" height="50" as="geometry"/></mxCell><mxCell id="98" style="relationshipConnector" parent="1" source="97" target="30" edge="1"><ErRelationshipConnector cardinalityMin="0" cardinalityMax="1" as="value"><ErRelationshipConnectorGBHandler as="erGraphBehaviourHandler"/></ErRelationshipConnector><mxGeometry relative="1" as="geometry"/></mxCell><mxCell id="99" style="relationshipConnector" parent="1" source="97" target="78" edge="1"><ErRelationshipConnector cardinalityMin="1" cardinalityMax="1" as="value"><ErRelationshipConnectorGBHandler as="erGraphBehaviourHandler"/></ErRelationshipConnector><mxGeometry relative="1" as="geometry"/></mxCell><mxCell id="100" style="relationship" parent="1" vertex="1"><ErRelationship name="ma zanr" as="value"><ErRelationshipGBHandler as="erGraphBehaviourHandler"/></ErRelationship><mxGeometry x="556" y="269.31" width="100" height="50" as="geometry"/></mxCell><mxCell id="101" style="relationshipConnector" parent="1" source="100" target="79" edge="1"><ErRelationshipConnector cardinalityMin="0" cardinalityMax="N" as="value"><ErRelationshipConnectorGBHandler as="erGraphBehaviourHandler"/></ErRelationshipConnector><mxGeometry relative="1" as="geometry"/></mxCell><mxCell id="102" style="relationshipConnector" parent="1" source="100" target="30" edge="1"><ErRelationshipConnector cardinalityMin="0" cardinalityMax="N" as="value"><ErRelationshipConnectorGBHandler as="erGraphBehaviourHandler"/></ErRelationshipConnector><mxGeometry relative="1" as="geometry"><Array as="points"><mxPoint x="606" y="223"/></Array></mxGeometry></mxCell><mxCell id="103" style="relationship" parent="1" vertex="1"><ErRelationship name="komentuje" as="value"><ErRelationshipGBHandler as="erGraphBehaviourHandler"/></ErRelationship><mxGeometry x="960" y="269.31" width="100" height="50" as="geometry"/></mxCell><mxCell id="104" style="relationshipConnector" parent="1" source="103" target="80" edge="1"><ErRelationshipConnector cardinalityMin="1" cardinalityMax="1" as="value"><ErRelationshipConnectorGBHandler as="erGraphBehaviourHandler"/></ErRelationshipConnector><mxGeometry relative="1" as="geometry"/></mxCell><mxCell id="105" style="relationshipConnector" parent="1" source="103" target="30" edge="1"><ErRelationshipConnector cardinalityMin="0" cardinalityMax="N" as="value"><ErRelationshipConnectorGBHandler as="erGraphBehaviourHandler"/></ErRelationshipConnector><mxGeometry relative="1" as="geometry"><Array as="points"><mxPoint x="1010" y="223"/></Array></mxGeometry></mxCell><mxCell id="106" style="attribute;attributeLabelBottom" parent="1" vertex="1" connectable="0"><ErAttribute name="obsah" as="value"><ErAttributeGBHandler as="erGraphBehaviourHandler"/></ErAttribute><mxGeometry x="1011" y="472" width="13" height="13" as="geometry"/></mxCell><mxCell id="107" style="attributeConnector" parent="1" source="106" target="80" edge="1"><ErAttributeConnector as="value"><ErAttributeConnectorGBHandler as="erGraphBehaviourHandler"/></ErAttributeConnector><mxGeometry relative="1" as="geometry"/></mxCell><mxCell id="108" style="entity" parent="1" vertex="1" connectable="0"><ErEntity name="Exemplar" as="value"><ErEntityGBHandler as="erGraphBehaviourHandler"/></ErEntity><mxGeometry x="321" y="205" width="100" height="40" as="geometry"/></mxCell><mxCell id="109" style="attribute;attributeLabelTop" parent="1" vertex="1" connectable="0"><ErAttribute name="cislo" as="value"><ErAttributeGBHandler as="erGraphBehaviourHandler"/></ErAttribute><mxGeometry x="315" y="136" width="13" height="13" as="geometry"/></mxCell><mxCell id="110" style="attributeConnector" parent="1" source="109" target="108" edge="1"><ErAttributeConnector as="value"><ErAttributeConnectorGBHandler as="erGraphBehaviourHandler"/></ErAttributeConnector><mxGeometry relative="1" as="geometry"/></mxCell><mxCell id="111" style="relationship" parent="1" vertex="1"><ErRelationship name="eviduje" as="value"><ErRelationshipGBHandler as="erGraphBehaviourHandler"/></ErRelationship><mxGeometry x="485" y="76" width="100" height="50" as="geometry"/></mxCell><mxCell id="112" style="relationshipConnector" parent="1" source="111" target="108" edge="1"><ErRelationshipConnector cardinalityMin="1" cardinalityMax="1" as="value"><ErRelationshipConnectorGBHandler as="erGraphBehaviourHandler"/></ErRelationshipConnector><mxGeometry relative="1" as="geometry"/></mxCell><mxCell id="113" style="relationshipConnector" parent="1" source="111" target="30" edge="1"><ErRelationshipConnector cardinalityMin="1" cardinalityMax="N" as="value"><ErRelationshipConnectorGBHandler as="erGraphBehaviourHandler"/></ErRelationshipConnector><mxGeometry relative="1" as="geometry"/></mxCell><mxCell id="114" style="compositeIdentifier" parent="1" vertex="1" connectable="0"><ErCompositeIdentifier as="value"><ErCompositeIdentifierGBHandler as="erGraphBehaviourHandler"/></ErCompositeIdentifier><mxGeometry as="geometry"><mxPoint x="329.59999999999997" y="181" as="sourcePoint"/><mxPoint x="385.8855182751974" y="181" as="targetPoint"/><Array as="points"><mxPoint x="344.59999999999997" y="181"/><mxPoint x="370.8855182751974" y="181"/></Array></mxGeometry></mxCell><mxCell id="115" parent="1" source="114" target="108" edge="1" visible="0"><ErCompositeIdentifierConnector as="value"><ErCompositeIdentifierConnectorGBHandler as="erGraphBehaviourHandler"/></ErCompositeIdentifierConnector><mxGeometry relative="1" as="geometry"/></mxCell><mxCell id="116" parent="1" source="114" target="110" edge="1" visible="0"><ErCompositeIdentifierMember as="value"><ErCompositeIdentifierMemberGBHandler as="erGraphBehaviourHandler"/></ErCompositeIdentifierMember><mxGeometry relative="1" as="geometry"/></mxCell><mxCell id="117" style="intersectionPoint" parent="1" vertex="1" connectable="0"><ErCompositeIdentifierIntersectionPoint as="value"><ErCompositeIdentifierIPointGBHandler as="erGraphBehaviourHandler"/></ErCompositeIdentifierIntersectionPoint><mxGeometry x="342.59999999999997" y="179" width="4" height="4" as="geometry"/></mxCell><mxCell id="118" parent="1" source="114" target="117" edge="1" visible="0"><ErCompositeIdentifierIntersectionPointConnector as="value"><ErCompositeIdentifierIPointConnectorGBHandler as="erGraphBehaviourHandler"/></ErCompositeIdentifierIntersectionPointConnector><mxGeometry relative="1" as="geometry"/></mxCell><mxCell id="119" parent="1" source="114" target="112" edge="1" visible="0"><ErCompositeIdentifierMember as="value"><ErCompositeIdentifierMemberGBHandler as="erGraphBehaviourHandler"/></ErCompositeIdentifierMember><mxGeometry relative="1" as="geometry"/></mxCell><mxCell id="120" style="intersectionPoint" parent="1" vertex="1" connectable="0"><ErCompositeIdentifierIntersectionPoint as="value"><ErCompositeIdentifierIPointGBHandler as="erGraphBehaviourHandler"/></ErCompositeIdentifierIntersectionPoint><mxGeometry x="368.8855182751974" y="179" width="4" height="4" as="geometry"/></mxCell><mxCell id="121" parent="1" source="114" target="120" edge="1" visible="0"><ErCompositeIdentifierIntersectionPointConnector as="value"><ErCompositeIdentifierIPointConnectorGBHandler as="erGraphBehaviourHandler"/></ErCompositeIdentifierIntersectionPointConnector><mxGeometry relative="1" as="geometry"/></mxCell><mxCell id="128" style="entity" parent="1" vertex="1" connectable="0"><ErEntity name="Uzivatel" as="value"><ErEntityGBHandler as="erGraphBehaviourHandler"/></ErEntity><mxGeometry x="745" y="607" width="100" height="40" as="geometry"/></mxCell><mxCell id="129" style="attribute;attributeIdentifier;attributeLabelTop" parent="1" vertex="1" connectable="0"><ErAttribute name="login" simpleIdentifier="1" as="value"><ErAttributeGBHandler as="erGraphBehaviourHandler"/></ErAttribute><mxGeometry x="805" y="583" width="13" height="13" as="geometry"/></mxCell><mxCell id="130" style="attributeConnector" parent="1" source="129" target="128" edge="1"><ErAttributeConnector as="value"><ErAttributeConnectorGBHandler as="erGraphBehaviourHandler"/></ErAttributeConnector><mxGeometry relative="1" as="geometry"/></mxCell><mxCell id="131" style="attribute;attributeLabelTop" parent="1" vertex="1" connectable="0"><ErAttribute name="heslo" as="value"><ErAttributeGBHandler as="erGraphBehaviourHandler"/></ErAttribute><mxGeometry x="756" y="577" width="13" height="13" as="geometry"/></mxCell><mxCell id="132" style="attributeConnector" parent="1" source="131" target="128" edge="1"><ErAttributeConnector as="value"><ErAttributeConnectorGBHandler as="erGraphBehaviourHandler"/></ErAttributeConnector><mxGeometry relative="1" as="geometry"/></mxCell><mxCell id="141" style="entity" parent="1" vertex="1" connectable="0"><ErEntity name="Osobni udaje" as="value"><ErEntityGBHandler as="erGraphBehaviourHandler"/></ErEntity><mxGeometry x="1042" y="607" width="100" height="40" as="geometry"/></mxCell><mxCell id="142" style="relationship" parent="1" vertex="1"><ErRelationship name="ma uchovane" as="value"><ErRelationshipGBHandler as="erGraphBehaviourHandler"/></ErRelationship><mxGeometry x="884" y="602" width="100" height="50" as="geometry"/></mxCell><mxCell id="143" style="relationshipConnector" parent="1" source="142" target="128" edge="1"><ErRelationshipConnector cardinalityMin="0" cardinalityMax="1" as="value"><ErRelationshipConnectorGBHandler as="erGraphBehaviourHandler"/></ErRelationshipConnector><mxGeometry relative="1" as="geometry"/></mxCell><mxCell id="144" style="relationshipConnector" parent="1" source="142" target="141" edge="1"><ErRelationshipConnector cardinalityMin="1" cardinalityMax="1" as="value"><ErRelationshipConnectorGBHandler as="erGraphBehaviourHandler"/></ErRelationshipConnector><mxGeometry relative="1" as="geometry"/></mxCell><mxCell id="145" style="attribute;attributeLabelBottom" parent="1" vertex="1" connectable="0"><ErAttribute name="jmeno" as="value"><ErAttributeGBHandler as="erGraphBehaviourHandler"/></ErAttribute><mxGeometry x="1173" y="651" width="13" height="13" as="geometry"/></mxCell><mxCell id="146" style="attributeConnector" parent="1" source="145" target="141" edge="1"><ErAttributeConnector as="value"><ErAttributeConnectorGBHandler as="erGraphBehaviourHandler"/></ErAttributeConnector><mxGeometry relative="1" as="geometry"/></mxCell><mxCell id="147" style="attribute;attributeLabelBottom" parent="1" vertex="1" connectable="0"><ErAttribute name="prijmeni" as="value"><ErAttributeGBHandler as="erGraphBehaviourHandler"/></ErAttribute><mxGeometry x="1144" y="675" width="13" height="13" as="geometry"/></mxCell><mxCell id="148" style="attributeConnector" parent="1" source="147" target="141" edge="1"><ErAttributeConnector as="value"><ErAttributeConnectorGBHandler as="erGraphBehaviourHandler"/></ErAttributeConnector><mxGeometry relative="1" as="geometry"/></mxCell><mxCell id="149" style="attribute;attributeLabelBottom" parent="1" vertex="1" connectable="0"><ErAttribute name="adresa" as="value"><ErAttributeGBHandler as="erGraphBehaviourHandler"/></ErAttribute><mxGeometry x="1099" y="687" width="13" height="13" as="geometry"/></mxCell><mxCell id="150" style="attributeConnector" parent="1" source="149" target="141" edge="1"><ErAttributeConnector as="value"><ErAttributeConnectorGBHandler as="erGraphBehaviourHandler"/></ErAttributeConnector><mxGeometry relative="1" as="geometry"/></mxCell><mxCell id="151" style="attribute;attributeLabelBottom" parent="1" vertex="1" connectable="0"><ErAttribute name="datum narozeni" as="value"><ErAttributeGBHandler as="erGraphBehaviourHandler"/></ErAttribute><mxGeometry x="1035" y="683.95" width="13" height="13" as="geometry"/></mxCell><mxCell id="152" style="attributeConnector" parent="1" source="151" target="141" edge="1"><ErAttributeConnector as="value"><ErAttributeConnectorGBHandler as="erGraphBehaviourHandler"/></ErAttributeConnector><mxGeometry relative="1" as="geometry"/></mxCell><mxCell id="170" style="attribute;attributeLabelTop" parent="1" vertex="1" connectable="0"><ErAttribute name="adresa" compositeAttribute="1" compositeAttributeRoot="1" as="value"><ErAttributeGBHandler as="erGraphBehaviourHandler"/></ErAttribute><mxGeometry x="1167" y="612" width="13" height="13" as="geometry"/></mxCell><mxCell id="171" style="attributeConnector" parent="1" source="170" target="141" edge="1"><ErAttributeConnector as="value"><ErAttributeConnectorGBHandler as="erGraphBehaviourHandler"/></ErAttributeConnector><mxGeometry relative="1" as="geometry"/></mxCell><mxCell id="172" style="attribute;attributeLabelTop" parent="1" vertex="1" connectable="0"><ErAttribute name="mesto" compositeAttribute="1" compositeAttributeMember="1" as="value"><ErAttributeGBHandler as="erGraphBehaviourHandler"/></ErAttribute><mxGeometry x="1217" y="576" width="13" height="13" as="geometry"/></mxCell><mxCell id="173" style="attributeConnector" parent="1" source="172" target="170" edge="1"><ErAttributeConnector as="value"><ErAttributeConnectorGBHandler as="erGraphBehaviourHandler"/></ErAttributeConnector><mxGeometry relative="1" as="geometry"/></mxCell><mxCell id="174" style="attribute;attributeLabelTop" parent="1" vertex="1" connectable="0"><ErAttribute name="ulice" compositeAttribute="1" compositeAttributeMember="1" as="value"><ErAttributeGBHandler as="erGraphBehaviourHandler"/></ErAttribute><mxGeometry x="1238" y="604" width="13" height="13" as="geometry"/></mxCell><mxCell id="175" style="attributeConnector" parent="1" source="174" target="170" edge="1"><ErAttributeConnector as="value"><ErAttributeConnectorGBHandler as="erGraphBehaviourHandler"/></ErAttributeConnector><mxGeometry relative="1" as="geometry"/></mxCell><mxCell id="176" style="attribute;attributeLabelBottom" parent="1" vertex="1" connectable="0"><ErAttribute name="c.p." compositeAttribute="1" compositeAttributeMember="1" as="value"><ErAttributeGBHandler as="erGraphBehaviourHandler"/></ErAttribute><mxGeometry x="1223" y="627" width="13" height="13" as="geometry"/></mxCell><mxCell id="177" style="attributeConnector" parent="1" source="176" target="170" edge="1"><ErAttributeConnector as="value"><ErAttributeConnectorGBHandler as="erGraphBehaviourHandler"/></ErAttributeConnector><mxGeometry relative="1" as="geometry"/></mxCell><mxCell id="198" style="compositeIdentifier" parent="1" vertex="1" connectable="0"><ErCompositeIdentifier as="value"><ErCompositeIdentifierGBHandler as="erGraphBehaviourHandler"/></ErCompositeIdentifier><mxGeometry as="geometry"><mxPoint x="1160.1924273692437" y="635.8161036517563" as="sourcePoint"/><mxPoint x="1046.627012993607" y="665.1924273692432" as="targetPoint"/><Array as="points"><mxPoint x="1160.1924273692434" y="650.8161036517563"/><mxPoint x="1160.1924273692432" y="665.1924273692432"/><mxPoint x="1142" y="665.1924273692432"/><mxPoint x="1132.9621314914395" y="665.1924273692432"/><mxPoint x="1061.627012993607" y="665.1924273692432"/></Array></mxGeometry></mxCell><mxCell id="199" parent="1" source="198" target="141" edge="1" visible="0"><ErCompositeIdentifierConnector as="value"><ErCompositeIdentifierConnectorGBHandler as="erGraphBehaviourHandler"/></ErCompositeIdentifierConnector><mxGeometry relative="1" as="geometry"/></mxCell><mxCell id="200" parent="1" source="198" target="152" edge="1" visible="0"><ErCompositeIdentifierMember as="value"><ErCompositeIdentifierMemberGBHandler as="erGraphBehaviourHandler"/></ErCompositeIdentifierMember><mxGeometry relative="1" as="geometry"/></mxCell><mxCell id="201" style="intersectionPoint" parent="1" vertex="1" connectable="0"><ErCompositeIdentifierIntersectionPoint as="value"><ErCompositeIdentifierIPointGBHandler as="erGraphBehaviourHandler"/></ErCompositeIdentifierIntersectionPoint><mxGeometry x="1059.627012993607" y="663.1924273692432" width="4" height="4" as="geometry"/></mxCell><mxCell id="202" parent="1" source="198" target="201" edge="1" visible="0"><ErCompositeIdentifierIntersectionPointConnector as="value"><ErCompositeIdentifierIPointConnectorGBHandler as="erGraphBehaviourHandler"/></ErCompositeIdentifierIntersectionPointConnector><mxGeometry relative="1" as="geometry"/></mxCell><mxCell id="203" parent="1" source="198" target="148" edge="1" visible="0"><ErCompositeIdentifierMember as="value"><ErCompositeIdentifierMemberGBHandler as="erGraphBehaviourHandler"/></ErCompositeIdentifierMember><mxGeometry relative="1" as="geometry"/></mxCell><mxCell id="204" style="intersectionPoint" parent="1" vertex="1" connectable="0"><ErCompositeIdentifierIntersectionPoint as="value"><ErCompositeIdentifierIPointGBHandler as="erGraphBehaviourHandler"/></ErCompositeIdentifierIntersectionPoint><mxGeometry x="1130.9621314914395" y="663.1924273692432" width="4" height="4" as="geometry"/></mxCell><mxCell id="205" parent="1" source="198" target="204" edge="1" visible="0"><ErCompositeIdentifierIntersectionPointConnector as="value"><ErCompositeIdentifierIPointConnectorGBHandler as="erGraphBehaviourHandler"/></ErCompositeIdentifierIntersectionPointConnector><mxGeometry relative="1" as="geometry"/></mxCell><mxCell id="206" parent="1" source="198" target="146" edge="1" visible="0"><ErCompositeIdentifierMember as="value"><ErCompositeIdentifierMemberGBHandler as="erGraphBehaviourHandler"/></ErCompositeIdentifierMember><mxGeometry relative="1" as="geometry"/></mxCell><mxCell id="207" style="intersectionPoint" parent="1" vertex="1" connectable="0"><ErCompositeIdentifierIntersectionPoint as="value"><ErCompositeIdentifierIPointGBHandler as="erGraphBehaviourHandler"/></ErCompositeIdentifierIntersectionPoint><mxGeometry x="1158.1924273692434" y="648.8161036517563" width="4" height="4" as="geometry"/></mxCell><mxCell id="208" parent="1" source="198" target="207" edge="1" visible="0"><ErCompositeIdentifierIntersectionPointConnector as="value"><ErCompositeIdentifierIPointConnectorGBHandler as="erGraphBehaviourHandler"/></ErCompositeIdentifierIntersectionPointConnector><mxGeometry relative="1" as="geometry"/></mxCell><mxCell id="209" style="entity" parent="1" vertex="1" connectable="0"><ErEntity name="Zamestnanec" as="value"><ErEntityGBHandler as="erGraphBehaviourHandler"/></ErEntity><mxGeometry x="605" y="816" width="100" height="40" as="geometry"/></mxCell><mxCell id="210" style="entity" parent="1" vertex="1" connectable="0"><ErEntity name="Zakaznik" as="value"><ErEntityGBHandler as="erGraphBehaviourHandler"/></ErEntity><mxGeometry x="857" y="816" width="100" height="40" as="geometry"/></mxCell><mxCell id="211" style="attribute;attributeLabelTop" parent="1" vertex="1" connectable="0"><ErAttribute name="mistnost" as="value"><ErAttributeGBHandler as="erGraphBehaviourHandler"/></ErAttribute><mxGeometry x="559" y="785" width="13" height="13" as="geometry"/></mxCell><mxCell id="212" style="attributeConnector" parent="1" source="211" target="209" edge="1"><ErAttributeConnector as="value"><ErAttributeConnectorGBHandler as="erGraphBehaviourHandler"/></ErAttributeConnector><mxGeometry relative="1" as="geometry"/></mxCell><mxCell id="213" style="attribute;attributeIdentifier;attributeLabelTop" parent="1" vertex="1" connectable="0"><ErAttribute name="rodne cislo" simpleIdentifier="1" as="value"><ErAttributeGBHandler as="erGraphBehaviourHandler"/></ErAttribute><mxGeometry x="582" y="759" width="13" height="13" as="geometry"/></mxCell><mxCell id="214" style="attributeConnector" parent="1" source="213" target="209" edge="1"><ErAttributeConnector as="value"><ErAttributeConnectorGBHandler as="erGraphBehaviourHandler"/></ErAttributeConnector><mxGeometry relative="1" as="geometry"/></mxCell><mxCell id="215" style="attribute;attributeLabelTop" parent="1" vertex="1" connectable="0"><ErAttribute name="interni telefon" as="value"><ErAttributeGBHandler as="erGraphBehaviourHandler"/></ErAttribute><mxGeometry x="504" y="797" width="13" height="13" as="geometry"/></mxCell><mxCell id="216" style="attributeConnector" parent="1" source="215" target="209" edge="1"><ErAttributeConnector as="value"><ErAttributeConnectorGBHandler as="erGraphBehaviourHandler"/></ErAttributeConnector><mxGeometry relative="1" as="geometry"/></mxCell><mxCell id="217" style="hierarchy" parent="1" vertex="1" connectable="0"><ErHierarchy coverage="Complete" disjointness="Overlapping" as="value"><ErHierarchyGBHandler as="erGraphBehaviourHandler"/></ErHierarchy><mxGeometry x="788.319243120399" y="756.0207882515685" width="10" height="10" as="geometry"/></mxCell><mxCell id="218" style="generalization" parent="1" source="217" target="128" edge="1"><ErGeneralizationConnector as="value"><ErGeneralizationConnectorGBHandler as="erGraphBehaviourHandler"/></ErGeneralizationConnector><mxGeometry relative="1" as="geometry"><Array as="points"><mxPoint x="793" y="675"/><mxPoint x="793" y="675"/></Array></mxGeometry></mxCell><mxCell id="219" style="specialization" parent="1" source="217" target="209" edge="1"><ErSpecializationConnector as="value"><ErSpecializationConnectorGBHandler as="erGraphBehaviourHandler"/></ErSpecializationConnector><mxGeometry relative="1" as="geometry"/></mxCell><mxCell id="220" style="specialization" parent="1" source="217" target="210" edge="1"><ErSpecializationConnector as="value"><ErSpecializationConnectorGBHandler as="erGraphBehaviourHandler"/></ErSpecializationConnector><mxGeometry relative="1" as="geometry"/></mxCell><mxCell id="221" style="attribute;attributeLabelBottom" parent="1" vertex="1" connectable="0"><ErAttribute name="sledujici" as="value"><ErAttributeGBHandler as="erGraphBehaviourHandler"/></ErAttribute><mxGeometry x="830" y="889" width="13" height="13" as="geometry"/></mxCell><mxCell id="222" style="attributeConnector" parent="1" source="221" target="210" edge="1"><ErAttributeConnector as="value"><ErAttributeConnectorGBHandler as="erGraphBehaviourHandler"/></ErAttributeConnector><mxGeometry relative="1" as="geometry"/></mxCell><mxCell id="226" style="relationship" parent="1" vertex="1"><ErRelationship name="zalozil" as="value"><ErRelationshipGBHandler as="erGraphBehaviourHandler"/></ErRelationship><mxGeometry x="731" y="811" width="100" height="50" as="geometry"/></mxCell><mxCell id="227" style="relationshipConnector" parent="1" source="226" target="209" edge="1"><ErRelationshipConnector cardinalityMin="1" cardinalityMax="N" as="value"><ErRelationshipConnectorGBHandler as="erGraphBehaviourHandler"/></ErRelationshipConnector><mxGeometry relative="1" as="geometry"/></mxCell><mxCell id="228" style="relationshipConnector" parent="1" source="226" target="210" edge="1"><ErRelationshipConnector cardinalityMin="1" cardinalityMax="1" as="value"><ErRelationshipConnectorGBHandler as="erGraphBehaviourHandler"/></ErRelationshipConnector><mxGeometry relative="1" as="geometry"/></mxCell><mxCell id="229" style="attribute;attributeLabelBottom" parent="1" vertex="1" connectable="0"><ErAttribute name="datum" as="value"><ErAttributeGBHandler as="erGraphBehaviourHandler"/></ErAttribute><mxGeometry x="762" y="883" width="13" height="13" as="geometry"/></mxCell><mxCell id="230" style="attributeConnector" parent="1" source="229" target="226" edge="1"><ErAttributeConnector as="value"><ErAttributeConnectorGBHandler as="erGraphBehaviourHandler"/></ErAttributeConnector><mxGeometry relative="1" as="geometry"/></mxCell><mxCell id="231" style="entity" parent="1" vertex="1" connectable="0"><ErEntity name="Zamestnanec" as="value"><ErEntityGBHandler as="erGraphBehaviourHandler"/></ErEntity><mxGeometry x="1719" y="190" width="100" height="40" as="geometry"/></mxCell><mxCell id="232" style="attribute;attributeIdentifier;attributeLabelTop" parent="1" vertex="1" connectable="0"><ErAttribute name="osobni cislo" simpleIdentifier="1" as="value"><ErAttributeGBHandler as="erGraphBehaviourHandler"/></ErAttribute><mxGeometry x="1849" y="155" width="13" height="13" as="geometry"/></mxCell><mxCell id="233" style="attributeConnector" parent="1" source="232" target="231" edge="1"><ErAttributeConnector as="value"><ErAttributeConnectorGBHandler as="erGraphBehaviourHandler"/></ErAttributeConnector><mxGeometry relative="1" as="geometry"/></mxCell><mxCell id="234" style="attribute;attributeLabelTop" parent="1" vertex="1" connectable="0"><ErAttribute name="stanoviste" as="value"><ErAttributeGBHandler as="erGraphBehaviourHandler"/></ErAttribute><mxGeometry x="1793" y="141" width="13" height="13" as="geometry"/></mxCell><mxCell id="235" style="attributeConnector" parent="1" source="234" target="231" edge="1"><ErAttributeConnector as="value"><ErAttributeConnectorGBHandler as="erGraphBehaviourHandler"/></ErAttributeConnector><mxGeometry relative="1" as="geometry"/></mxCell><mxCell id="239" style="entity" parent="1" vertex="1" connectable="0"><ErEntity name="Zakaznik" as="value"><ErEntityGBHandler as="erGraphBehaviourHandler"/></ErEntity><mxGeometry x="1719" y="386" width="100" height="40" as="geometry"/></mxCell><mxCell id="241" style="relationship" parent="1" vertex="1"><ErRelationship name="odbavuje" as="value"><ErRelationshipGBHandler as="erGraphBehaviourHandler"/></ErRelationship><mxGeometry x="1719" y="281" width="100" height="50" as="geometry"/></mxCell><mxCell id="242" style="relationshipConnector" parent="1" source="241" target="231" edge="1"><ErRelationshipConnector cardinalityMin="1" cardinalityMax="1" as="value"><ErRelationshipConnectorGBHandler as="erGraphBehaviourHandler"/></ErRelationshipConnector><mxGeometry relative="1" as="geometry"/></mxCell><mxCell id="243" style="relationshipConnector" parent="1" source="241" target="239" edge="1"><ErRelationshipConnector cardinalityMin="1" cardinalityMax="1" as="value"><ErRelationshipConnectorGBHandler as="erGraphBehaviourHandler"/></ErRelationshipConnector><mxGeometry relative="1" as="geometry"/></mxCell><mxCell id="244" style="attribute;attributeLabelBottom" parent="1" vertex="1" connectable="0"><ErAttribute name="cislo pasu" as="value"><ErAttributeGBHandler as="erGraphBehaviourHandler"/></ErAttribute><mxGeometry x="1667" y="460" width="13" height="13" as="geometry"/></mxCell><mxCell id="245" style="attributeConnector" parent="1" source="244" target="239" edge="1"><ErAttributeConnector as="value"><ErAttributeConnectorGBHandler as="erGraphBehaviourHandler"/></ErAttributeConnector><mxGeometry relative="1" as="geometry"/></mxCell><mxCell id="246" style="attribute;attributeLabelBottom" parent="1" vertex="1" connectable="0"><ErAttribute name="informace o letu" compositeAttribute="1" compositeAttributeRoot="1" as="value"><ErAttributeGBHandler as="erGraphBehaviourHandler"/></ErAttribute><mxGeometry x="1752" y="461.79" width="13" height="13" as="geometry"/></mxCell><mxCell id="247" style="attributeConnector" parent="1" source="246" target="239" edge="1"><ErAttributeConnector as="value"><ErAttributeConnectorGBHandler as="erGraphBehaviourHandler"/></ErAttributeConnector><mxGeometry relative="1" as="geometry"/></mxCell><mxCell id="248" style="attribute;attributeLabelBottom" parent="1" vertex="1" connectable="0"><ErAttribute name="jmeno" as="value"><ErAttributeGBHandler as="erGraphBehaviourHandler"/></ErAttribute><mxGeometry x="1859" y="430" width="13" height="13" as="geometry"/></mxCell><mxCell id="249" style="attributeConnector" parent="1" source="248" target="239" edge="1"><ErAttributeConnector as="value"><ErAttributeConnectorGBHandler as="erGraphBehaviourHandler"/></ErAttributeConnector><mxGeometry relative="1" as="geometry"/></mxCell><mxCell id="250" style="attribute;attributeLabelBottom" parent="1" vertex="1" connectable="0"><ErAttribute name="cislo letu" compositeAttribute="1" compositeAttributeMember="1" as="value"><ErAttributeGBHandler as="erGraphBehaviourHandler"/></ErAttribute><mxGeometry x="1708" y="516" width="13" height="13" as="geometry"/></mxCell><mxCell id="251" style="attributeConnector" parent="1" source="250" target="246" edge="1"><ErAttributeConnector as="value"><ErAttributeConnectorGBHandler as="erGraphBehaviourHandler"/></ErAttributeConnector><mxGeometry relative="1" as="geometry"/></mxCell><mxCell id="252" style="attribute;attributeLabelBottom" parent="1" vertex="1" connectable="0"><ErAttribute name="datum" compositeAttribute="1" compositeAttributeMember="1" as="value"><ErAttributeGBHandler as="erGraphBehaviourHandler"/></ErAttribute><mxGeometry x="1770" y="520" width="13" height="13" as="geometry"/></mxCell><mxCell id="253" style="attributeConnector" parent="1" source="252" target="246" edge="1"><ErAttributeConnector as="value"><ErAttributeConnectorGBHandler as="erGraphBehaviourHandler"/></ErAttributeConnector><mxGeometry relative="1" as="geometry"/></mxCell><mxCell id="254" style="attribute;attributeLabelBottom" parent="1" vertex="1" connectable="0"><ErAttribute name="pridelene sedadlo" as="value"><ErAttributeGBHandler as="erGraphBehaviourHandler"/></ErAttribute><mxGeometry x="1820" y="447.52" width="13" height="13" as="geometry"/></mxCell><mxCell id="255" style="attributeConnector" parent="1" source="254" target="239" edge="1"><ErAttributeConnector as="value"><ErAttributeConnectorGBHandler as="erGraphBehaviourHandler"/></ErAttributeConnector><mxGeometry relative="1" as="geometry"/></mxCell><mxCell id="256" style="compositeIdentifier" parent="1" vertex="1" connectable="0"><ErCompositeIdentifier as="value"><ErCompositeIdentifierGBHandler as="erGraphBehaviourHandler"/></ErCompositeIdentifier><mxGeometry as="geometry"><mxPoint x="1776.9640574790753" y="447.5235354475153" as="sourcePoint"/><mxPoint x="1688.436579434698" y="447.5235354475153" as="targetPoint"/><Array as="points"><mxPoint x="1761.9640574790753" y="447.5235354475153"/><mxPoint x="1719" y="447.5235354475153"/><mxPoint x="1703.436579434698" y="447.5235354475153"/></Array></mxGeometry></mxCell><mxCell id="257" parent="1" source="256" target="239" edge="1" visible="0"><ErCompositeIdentifierConnector as="value"><ErCompositeIdentifierConnectorGBHandler as="erGraphBehaviourHandler"/></ErCompositeIdentifierConnector><mxGeometry relative="1" as="geometry"/></mxCell><mxCell id="258" parent="1" source="256" target="245" edge="1" visible="0"><ErCompositeIdentifierMember as="value"><ErCompositeIdentifierMemberGBHandler as="erGraphBehaviourHandler"/></ErCompositeIdentifierMember><mxGeometry relative="1" as="geometry"/></mxCell><mxCell id="259" style="intersectionPoint" parent="1" vertex="1" connectable="0"><ErCompositeIdentifierIntersectionPoint as="value"><ErCompositeIdentifierIPointGBHandler as="erGraphBehaviourHandler"/></ErCompositeIdentifierIntersectionPoint><mxGeometry x="1701.436579434698" y="445.5235354475153" width="4" height="4" as="geometry"/></mxCell><mxCell id="260" parent="1" source="256" target="259" edge="1" visible="0"><ErCompositeIdentifierIntersectionPointConnector as="value"><ErCompositeIdentifierIPointConnectorGBHandler as="erGraphBehaviourHandler"/></ErCompositeIdentifierIntersectionPointConnector><mxGeometry relative="1" as="geometry"/></mxCell><mxCell id="261" parent="1" source="256" target="247" edge="1" visible="0"><ErCompositeIdentifierMember as="value"><ErCompositeIdentifierMemberGBHandler as="erGraphBehaviourHandler"/></ErCompositeIdentifierMember><mxGeometry relative="1" as="geometry"/></mxCell><mxCell id="262" style="intersectionPoint" parent="1" vertex="1" connectable="0"><ErCompositeIdentifierIntersectionPoint as="value"><ErCompositeIdentifierIPointGBHandler as="erGraphBehaviourHandler"/></ErCompositeIdentifierIntersectionPoint><mxGeometry x="1759.9640574790753" y="445.5235354475153" width="4" height="4" as="geometry"/></mxCell><mxCell id="263" parent="1" source="256" target="262" edge="1" visible="0"><ErCompositeIdentifierIntersectionPointConnector as="value"><ErCompositeIdentifierIPointConnectorGBHandler as="erGraphBehaviourHandler"/></ErCompositeIdentifierIntersectionPointConnector><mxGeometry relative="1" as="geometry"/></mxCell><mxCell id="264" style="entity" parent="1" vertex="1" connectable="0"><ErEntity name="Zavazadlo" as="value"><ErEntityGBHandler as="erGraphBehaviourHandler"/></ErEntity><mxGeometry x="2128" y="386" width="100" height="40" as="geometry"/></mxCell><mxCell id="265" style="relationship" parent="1" vertex="1"><ErRelationship name="prevazi" as="value"><ErRelationshipGBHandler as="erGraphBehaviourHandler"/></ErRelationship><mxGeometry x="1922" y="380.95" width="100" height="50" as="geometry"/></mxCell><mxCell id="266" style="relationshipConnector" parent="1" source="265" target="239" edge="1"><ErRelationshipConnector cardinalityMin="1" cardinalityMax="N" as="value"><ErRelationshipConnectorGBHandler as="erGraphBehaviourHandler"/></ErRelationshipConnector><mxGeometry relative="1" as="geometry"/></mxCell><mxCell id="267" style="relationshipConnector" parent="1" source="265" target="264" edge="1"><ErRelationshipConnector cardinalityMin="0" cardinalityMax="N" as="value"><ErRelationshipConnectorGBHandler as="erGraphBehaviourHandler"/></ErRelationshipConnector><mxGeometry relative="1" as="geometry"/></mxCell><mxCell id="268" style="attribute;attributeLabelTop" parent="1" vertex="1" connectable="0"><ErAttribute name="udaje majitele" compositeAttribute="1" compositeAttributeRoot="1" as="value"><ErAttributeGBHandler as="erGraphBehaviourHandler"/></ErAttribute><mxGeometry x="2236" y="346" width="13" height="13" as="geometry"/></mxCell><mxCell id="269" style="attributeConnector" parent="1" source="268" target="264" edge="1"><ErAttributeConnector as="value"><ErAttributeConnectorGBHandler as="erGraphBehaviourHandler"/></ErAttributeConnector><mxGeometry relative="1" as="geometry"/></mxCell><mxCell id="270" style="attribute;attributeLabelTop" parent="1" vertex="1" connectable="0"><ErAttribute name="informace o letu" compositeAttribute="1" compositeAttributeRoot="1" as="value"><ErAttributeGBHandler as="erGraphBehaviourHandler"/></ErAttribute><mxGeometry x="2273" y="397" width="13" height="13" as="geometry"/></mxCell><mxCell id="271" style="attributeConnector" parent="1" source="270" target="264" edge="1"><ErAttributeConnector as="value"><ErAttributeConnectorGBHandler as="erGraphBehaviourHandler"/></ErAttributeConnector><mxGeometry relative="1" as="geometry"/></mxCell><mxCell id="272" style="attribute;attributeLabelTop" parent="1" vertex="1" connectable="0"><ErAttribute name="cislo letu" compositeAttribute="1" compositeAttributeMember="1" as="value"><ErAttributeGBHandler as="erGraphBehaviourHandler"/></ErAttribute><mxGeometry x="2336" y="370" width="13" height="13" as="geometry"/></mxCell><mxCell id="273" style="attributeConnector" parent="1" source="272" target="270" edge="1"><ErAttributeConnector as="value"><ErAttributeConnectorGBHandler as="erGraphBehaviourHandler"/></ErAttributeConnector><mxGeometry relative="1" as="geometry"/></mxCell><mxCell id="274" style="attribute;attributeLabelBottom" parent="1" vertex="1" connectable="0"><ErAttribute name="datum" compositeAttribute="1" compositeAttributeMember="1" as="value"><ErAttributeGBHandler as="erGraphBehaviourHandler"/></ErAttribute><mxGeometry x="2349" y="400.95" width="13" height="13" as="geometry"/></mxCell><mxCell id="275" style="attributeConnector" parent="1" source="274" target="270" edge="1"><ErAttributeConnector as="value"><ErAttributeConnectorGBHandler as="erGraphBehaviourHandler"/></ErAttributeConnector><mxGeometry relative="1" as="geometry"/></mxCell><mxCell id="276" style="attribute;attributeLabelTop" parent="1" vertex="1" connectable="0"><ErAttribute name="cislo pasu" compositeAttribute="1" compositeAttributeMember="1" as="value"><ErAttributeGBHandler as="erGraphBehaviourHandler"/></ErAttribute><mxGeometry x="2234" y="310" width="13" height="13" as="geometry"/></mxCell><mxCell id="277" style="attributeConnector" parent="1" source="276" target="268" edge="1"><ErAttributeConnector as="value"><ErAttributeConnectorGBHandler as="erGraphBehaviourHandler"/></ErAttributeConnector><mxGeometry relative="1" as="geometry"/></mxCell><mxCell id="278" style="attribute;attributeLabelTop" parent="1" vertex="1" connectable="0"><ErAttribute name="jmeno" compositeAttribute="1" compositeAttributeMember="1" as="value"><ErAttributeGBHandler as="erGraphBehaviourHandler"/></ErAttribute><mxGeometry x="2288" y="320" width="13" height="13" as="geometry"/></mxCell><mxCell id="279" style="attributeConnector" parent="1" source="278" target="268" edge="1"><ErAttributeConnector as="value"><ErAttributeConnectorGBHandler as="erGraphBehaviourHandler"/></ErAttributeConnector><mxGeometry relative="1" as="geometry"/></mxCell><mxCell id="280" style="compositeIdentifier" parent="1" vertex="1" connectable="0"><ErCompositeIdentifier as="value"><ErCompositeIdentifierGBHandler as="erGraphBehaviourHandler"/></ErCompositeIdentifier><mxGeometry as="geometry"><mxPoint x="2209.4208578970815" y="367.48856636664334" as="sourcePoint"/><mxPoint x="2246.511433633356" y="419.2604188948237" as="targetPoint"/><Array as="points"><mxPoint x="2224.4208578970815" y="367.48856636664334"/><mxPoint x="2228" y="367.48856636664334"/><mxPoint x="2246.511433633357" y="367.48856636664334"/><mxPoint x="2246.511433633357" y="386"/><mxPoint x="2246.5114336333563" y="404.2604188948237"/></Array></mxGeometry></mxCell><mxCell id="281" parent="1" source="280" target="264" edge="1" visible="0"><ErCompositeIdentifierConnector as="value"><ErCompositeIdentifierConnectorGBHandler as="erGraphBehaviourHandler"/></ErCompositeIdentifierConnector><mxGeometry relative="1" as="geometry"/></mxCell><mxCell id="282" parent="1" source="280" target="269" edge="1" visible="0"><ErCompositeIdentifierMember as="value"><ErCompositeIdentifierMemberGBHandler as="erGraphBehaviourHandler"/></ErCompositeIdentifierMember><mxGeometry relative="1" as="geometry"/></mxCell><mxCell id="283" style="intersectionPoint" parent="1" vertex="1" connectable="0"><ErCompositeIdentifierIntersectionPoint as="value"><ErCompositeIdentifierIPointGBHandler as="erGraphBehaviourHandler"/></ErCompositeIdentifierIntersectionPoint><mxGeometry x="2222.4208578970815" y="365.48856636664334" width="4" height="4" as="geometry"/></mxCell><mxCell id="284" parent="1" source="280" target="283" edge="1" visible="0"><ErCompositeIdentifierIntersectionPointConnector as="value"><ErCompositeIdentifierIPointConnectorGBHandler as="erGraphBehaviourHandler"/></ErCompositeIdentifierIntersectionPointConnector><mxGeometry relative="1" as="geometry"/></mxCell><mxCell id="285" parent="1" source="280" target="271" edge="1" visible="0"><ErCompositeIdentifierMember as="value"><ErCompositeIdentifierMemberGBHandler as="erGraphBehaviourHandler"/></ErCompositeIdentifierMember><mxGeometry relative="1" as="geometry"/></mxCell><mxCell id="286" style="intersectionPoint" parent="1" vertex="1" connectable="0"><ErCompositeIdentifierIntersectionPoint as="value"><ErCompositeIdentifierIPointGBHandler as="erGraphBehaviourHandler"/></ErCompositeIdentifierIntersectionPoint><mxGeometry x="2244.5114336333563" y="402.2604188948237" width="4" height="4" as="geometry"/></mxCell><mxCell id="287" parent="1" source="280" target="286" edge="1" visible="0"><ErCompositeIdentifierIntersectionPointConnector as="value"><ErCompositeIdentifierIPointConnectorGBHandler as="erGraphBehaviourHandler"/></ErCompositeIdentifierIntersectionPointConnector><mxGeometry relative="1" as="geometry"/></mxCell><mxCell id="288" style="attribute;attributeLabelTop" parent="1" vertex="1" connectable="0"><ErAttribute name="hmotnost" as="value"><ErAttributeGBHandler as="erGraphBehaviourHandler"/></ErAttribute><mxGeometry x="2169" y="348" width="13" height="13" as="geometry"/></mxCell><mxCell id="289" style="attributeConnector" parent="1" source="288" target="264" edge="1"><ErAttributeConnector as="value"><ErAttributeConnectorGBHandler as="erGraphBehaviourHandler"/></ErAttributeConnector><mxGeometry relative="1" as="geometry"/></mxCell><mxCell id="290" style="entity" parent="1" vertex="1" connectable="0"><ErEntity name="Trida v letadle" as="value"><ErEntityGBHandler as="erGraphBehaviourHandler"/></ErEntity><mxGeometry x="1456" y="386" width="100" height="40" as="geometry"/></mxCell><mxCell id="291" style="relationship" parent="1" vertex="1"><ErRelationship name="sedi v" as="value"><ErRelationshipGBHandler as="erGraphBehaviourHandler"/></ErRelationship><mxGeometry x="1588" y="381" width="100" height="50" as="geometry"/></mxCell><mxCell id="292" style="relationshipConnector" parent="1" source="291" target="290" edge="1"><ErRelationshipConnector cardinalityMin="1" cardinalityMax="1" as="value"><ErRelationshipConnectorGBHandler as="erGraphBehaviourHandler"/></ErRelationshipConnector><mxGeometry relative="1" as="geometry"/></mxCell><mxCell id="293" style="relationshipConnector" parent="1" source="291" target="239" edge="1"><ErRelationshipConnector cardinalityMin="0" cardinalityMax="N" as="value"><ErRelationshipConnectorGBHandler as="erGraphBehaviourHandler"/></ErRelationshipConnector><mxGeometry relative="1" as="geometry"/></mxCell><mxCell id="294" style="attribute;attributeLabelTop;attributeIdentifier" parent="1" vertex="1" connectable="0"><ErAttribute name="cislo tridy" simpleIdentifier="1" as="value"><ErAttributeGBHandler as="erGraphBehaviourHandler"/></ErAttribute><mxGeometry x="1529" y="345" width="13" height="13" as="geometry"/></mxCell><mxCell id="295" style="attributeConnector" parent="1" source="294" target="290" edge="1"><ErAttributeConnector as="value"><ErAttributeConnectorGBHandler as="erGraphBehaviourHandler"/></ErAttributeConnector><mxGeometry relative="1" as="geometry"/></mxCell><mxCell id="296" style="attribute;attributeLabelTop" parent="1" vertex="1" connectable="0"><ErAttribute name="jidelnicek" as="value"><ErAttributeGBHandler as="erGraphBehaviourHandler"/></ErAttribute><mxGeometry x="1470" y="343" width="13" height="13" as="geometry"/></mxCell><mxCell id="297" style="attributeConnector" parent="1" source="296" target="290" edge="1"><ErAttributeConnector as="value"><ErAttributeConnectorGBHandler as="erGraphBehaviourHandler"/></ErAttributeConnector><mxGeometry relative="1" as="geometry"/></mxCell><mxCell id="300" style="attribute;attributeLabelTop" parent="1" vertex="1" connectable="0"><ErAttribute name="statistika poctu odbavenych lidi" as="value"><ErAttributeGBHandler as="erGraphBehaviourHandler"/></ErAttribute><mxGeometry x="1855" y="281" width="13" height="13" as="geometry"/></mxCell><mxCell id="301" style="attributeConnector" parent="1" source="300" target="241" edge="1"><ErAttributeConnector as="value"><ErAttributeConnectorGBHandler as="erGraphBehaviourHandler"/></ErAttributeConnector><mxGeometry relative="1" as="geometry"/></mxCell><mxCell id="302" style="attribute;attributeLabelTop" parent="1" vertex="1" connectable="0"><ErAttribute name="vaha zavazadla" as="value"><ErAttributeGBHandler as="erGraphBehaviourHandler"/></ErAttribute><mxGeometry x="2004" y="357" width="13" height="13" as="geometry"/></mxCell><mxCell id="303" style="attributeConnector" parent="1" source="302" target="265" edge="1"><ErAttributeConnector as="value"><ErAttributeConnectorGBHandler as="erGraphBehaviourHandler"/></ErAttributeConnector><mxGeometry relative="1" as="geometry"/></mxCell><mxCell id="304" style="attribute;attributeIdentifier;attributeLabelBottom" parent="1" vertex="1" connectable="0"><ErAttribute name="poznavaci cislo" simpleIdentifier="1" as="value"><ErAttributeGBHandler as="erGraphBehaviourHandler"/></ErAttribute><mxGeometry x="2204" y="441.02" width="13" height="13" as="geometry"/></mxCell><mxCell id="305" style="attributeConnector" parent="1" source="304" target="264" edge="1"><ErAttributeConnector as="value"><ErAttributeConnectorGBHandler as="erGraphBehaviourHandler"/></ErAttributeConnector><mxGeometry relative="1" as="geometry"/></mxCell><mxCell id="306" style="entity" vertex="1" connectable="0" parent="1"><ErEntity name="Clensky prispevek" as="value"><ErEntityGBHandler as="erGraphBehaviourHandler"/></ErEntity><mxGeometry x="857" y="997" width="100" height="40" as="geometry"/></mxCell><mxCell id="307" style="attribute;attributeLabelBottom" vertex="1" connectable="0" parent="1"><ErAttribute name="cena" as="value"><ErAttributeGBHandler as="erGraphBehaviourHandler"/></ErAttribute><mxGeometry x="840.35" y="1055" width="13" height="13" as="geometry"/></mxCell><mxCell id="308" style="attributeConnector" edge="1" parent="1" source="307" target="306"><ErAttributeConnector as="value"><ErAttributeConnectorGBHandler as="erGraphBehaviourHandler"/></ErAttributeConnector><mxGeometry relative="1" as="geometry"/></mxCell><mxCell id="309" style="relationship" vertex="1" parent="1"><ErRelationship name="zaplatil" as="value"><ErRelationshipGBHandler as="erGraphBehaviourHandler"/></ErRelationship><mxGeometry x="857" y="897" width="100" height="50" as="geometry"/></mxCell><mxCell id="310" style="relationshipConnector" edge="1" parent="1" source="309" target="306"><ErRelationshipConnector cardinalityMin="1" cardinalityMax="1" as="value"><ErRelationshipConnectorGBHandler as="erGraphBehaviourHandler"/></ErRelationshipConnector><mxGeometry relative="1" as="geometry"/></mxCell><mxCell id="311" style="relationshipConnector" edge="1" parent="1" source="309" target="210"><ErRelationshipConnector cardinalityMin="0" cardinalityMax="N" as="value"><ErRelationshipConnectorGBHandler as="erGraphBehaviourHandler"/></ErRelationshipConnector><mxGeometry relative="1" as="geometry"/></mxCell><mxCell id="317" style="attribute;attributeLabelBottom" vertex="1" connectable="0" parent="1"><ErAttribute name="od" as="value"><ErAttributeGBHandler as="erGraphBehaviourHandler"/></ErAttribute><mxGeometry x="961" y="1059" width="13" height="13" as="geometry"/></mxCell><mxCell id="318" style="attributeConnector" edge="1" parent="1" source="317" target="306"><ErAttributeConnector as="value"><ErAttributeConnectorGBHandler as="erGraphBehaviourHandler"/></ErAttributeConnector><mxGeometry relative="1" as="geometry"/></mxCell><mxCell id="319" style="attribute;attributeLabelBottom" vertex="1" connectable="0" parent="1"><ErAttribute name="do" as="value"><ErAttributeGBHandler as="erGraphBehaviourHandler"/></ErAttribute><mxGeometry x="984" y="1039" width="13" height="13" as="geometry"/></mxCell><mxCell id="320" style="attributeConnector" edge="1" parent="1" source="319" target="306"><ErAttributeConnector as="value"><ErAttributeConnectorGBHandler as="erGraphBehaviourHandler"/></ErAttributeConnector><mxGeometry relative="1" as="geometry"/></mxCell><mxCell id="329" style="attribute;attributeLabelTop" vertex="1" connectable="0" parent="1"><ErAttribute name="rok" as="value"><ErAttributeGBHandler as="erGraphBehaviourHandler"/></ErAttribute><mxGeometry x="1002" y="973" width="13" height="13" as="geometry"/></mxCell><mxCell id="330" style="attributeConnector" edge="1" parent="1" source="329" target="306"><ErAttributeConnector as="value"><ErAttributeConnectorGBHandler as="erGraphBehaviourHandler"/></ErAttributeConnector><mxGeometry relative="1" as="geometry"/></mxCell><mxCell id="331" style="compositeIdentifier" vertex="1" connectable="0" parent="1"><ErCompositeIdentifier as="value"><ErCompositeIdentifierGBHandler as="erGraphBehaviourHandler"/></ErCompositeIdentifier><mxGeometry as="geometry"><mxPoint x="892" y="973" as="sourcePoint"/><mxPoint x="981" y="1004.6242834704101" as="targetPoint"/><Array as="points"><mxPoint x="907" y="973"/><mxPoint x="957" y="973"/><mxPoint x="981" y="973"/><mxPoint x="981" y="989.6242834704101"/></Array></mxGeometry></mxCell><mxCell id="332" edge="1" parent="1" source="331" target="306" visible="0"><ErCompositeIdentifierConnector as="value"><ErCompositeIdentifierConnectorGBHandler as="erGraphBehaviourHandler"/></ErCompositeIdentifierConnector><mxGeometry relative="1" as="geometry"/></mxCell><mxCell id="333" edge="1" parent="1" source="331" target="330" visible="0"><ErCompositeIdentifierMember as="value"><ErCompositeIdentifierMemberGBHandler as="erGraphBehaviourHandler"/></ErCompositeIdentifierMember><mxGeometry relative="1" as="geometry"/></mxCell><mxCell id="334" style="intersectionPoint" vertex="1" connectable="0" parent="1"><ErCompositeIdentifierIntersectionPoint as="value"><ErCompositeIdentifierIPointGBHandler as="erGraphBehaviourHandler"/></ErCompositeIdentifierIntersectionPoint><mxGeometry x="979" y="987.6242834704101" width="4" height="4" as="geometry"/></mxCell><mxCell id="335" edge="1" parent="1" source="331" target="334" visible="0"><ErCompositeIdentifierIntersectionPointConnector as="value"><ErCompositeIdentifierIPointConnectorGBHandler as="erGraphBehaviourHandler"/></ErCompositeIdentifierIntersectionPointConnector><mxGeometry relative="1" as="geometry"/></mxCell><mxCell id="336" edge="1" parent="1" source="331" target="310" visible="0"><ErCompositeIdentifierMember as="value"><ErCompositeIdentifierMemberGBHandler as="erGraphBehaviourHandler"/></ErCompositeIdentifierMember><mxGeometry relative="1" as="geometry"/></mxCell><mxCell id="337" style="intersectionPoint" vertex="1" connectable="0" parent="1"><ErCompositeIdentifierIntersectionPoint as="value"><ErCompositeIdentifierIPointGBHandler as="erGraphBehaviourHandler"/></ErCompositeIdentifierIntersectionPoint><mxGeometry x="905" y="971" width="4" height="4" as="geometry"/></mxCell><mxCell id="338" edge="1" parent="1" source="331" target="337" visible="0"><ErCompositeIdentifierIntersectionPointConnector as="value"><ErCompositeIdentifierIPointConnectorGBHandler as="erGraphBehaviourHandler"/></ErCompositeIdentifierIntersectionPointConnector><mxGeometry relative="1" as="geometry"/></mxCell><mxCell id="339" style="relationship" vertex="1" parent="1"><ErRelationship name="rezervuje" as="value"><ErRelationshipGBHandler as="erGraphBehaviourHandler"/></ErRelationship><mxGeometry x="1278.9999999999998" y="474.79" width="100" height="50" as="geometry"/></mxCell><mxCell id="340" style="relationshipConnector" edge="1" parent="1" source="339" target="210"><ErRelationshipConnector cardinalityMin="0" cardinalityMax="N" as="value"><ErRelationshipConnectorGBHandler as="erGraphBehaviourHandler"/></ErRelationshipConnector><mxGeometry relative="1" as="geometry"><Array as="points"><mxPoint x="1329" y="824"/></Array></mxGeometry></mxCell><mxCell id="341" style="relationshipConnector" edge="1" parent="1" source="339" target="30"><ErRelationshipConnector cardinalityMin="0" cardinalityMax="N" as="value"><ErRelationshipConnectorGBHandler as="erGraphBehaviourHandler"/></ErRelationshipConnector><mxGeometry relative="1" as="geometry"><Array as="points"><mxPoint x="1329" y="208"/></Array></mxGeometry></mxCell><mxCell id="342" style="relationship" vertex="1" parent="1"><ErRelationship name="vytvarii" as="value"><ErRelationshipGBHandler as="erGraphBehaviourHandler"/></ErRelationship><mxGeometry x="851.05" y="406.26" width="100" height="50" as="geometry"/></mxCell><mxCell id="343" style="relationshipConnector" edge="1" parent="1" source="342" target="210"><ErRelationshipConnector cardinalityMin="0" cardinalityMax="N" as="value"><ErRelationshipConnectorGBHandler as="erGraphBehaviourHandler"/></ErRelationshipConnector><mxGeometry relative="1" as="geometry"><Array as="points"><mxPoint x="873" y="457"/><mxPoint x="873" y="668"/><mxPoint x="907" y="668"/></Array></mxGeometry></mxCell><mxCell id="344" style="relationshipConnector" edge="1" parent="1" source="342" target="80"><ErRelationshipConnector cardinalityMin="1" cardinalityMax="1" as="value"><ErRelationshipConnectorGBHandler as="erGraphBehaviourHandler"/></ErRelationshipConnector><mxGeometry relative="1" as="geometry"/></mxCell><mxCell id="346" style="relationship" vertex="1" parent="1"><ErRelationship name="je nadzanr" as="value"><ErRelationshipGBHandler as="erGraphBehaviourHandler"/></ErRelationship><mxGeometry x="463" y="462" width="100" height="50" as="geometry"/></mxCell><mxCell id="347" style="relationshipConnector" edge="1" parent="1" source="346" target="79"><ErRelationshipConnector cardinalityMin="0" cardinalityMax="1" as="value"><ErRelationshipConnectorGBHandler as="erGraphBehaviourHandler"/></ErRelationshipConnector><mxGeometry relative="1" as="geometry"><Array as="points"><mxPoint x="575" y="487"/><mxPoint x="606" y="488"/></Array></mxGeometry></mxCell><mxCell id="348" style="relationshipConnector" edge="1" parent="1" source="346" target="79"><ErRelationshipConnector cardinalityMin="0" cardinalityMax="N" as="value"><ErRelationshipConnectorGBHandler as="erGraphBehaviourHandler"/></ErRelationshipConnector><mxGeometry relative="1" as="geometry"><Array as="points"><mxPoint x="442" y="428"/></Array></mxGeometry></mxCell><mxCell id="357" style="relationship" vertex="1" parent="1"><ErRelationship name="je nadrizeny" as="value"><ErRelationshipGBHandler as="erGraphBehaviourHandler"/></ErRelationship><mxGeometry x="493" y="928" width="100" height="50" as="geometry"/></mxCell><mxCell id="358" style="relationshipConnector" edge="1" parent="1" source="357" target="209"><ErRelationshipConnector cardinalityMin="0" cardinalityMax="N" as="value"><ErRelationshipConnectorGBHandler as="erGraphBehaviourHandler"/></ErRelationshipConnector><mxGeometry relative="1" as="geometry"><Array as="points"><mxPoint x="690" y="953"/></Array></mxGeometry></mxCell><mxCell id="359" style="relationshipConnector" edge="1" parent="1" source="357" target="209"><ErRelationshipConnector cardinalityMin="0" cardinalityMax="1" as="value"><ErRelationshipConnectorGBHandler as="erGraphBehaviourHandler"/></ErRelationshipConnector><mxGeometry relative="1" as="geometry"><Array as="points"><mxPoint x="543" y="864"/><mxPoint x="655" y="864"/></Array></mxGeometry></mxCell><mxCell id="360" style="relationship" vertex="1" parent="1"><ErRelationship name="doporucuje" as="value"><ErRelationshipGBHandler as="erGraphBehaviourHandler"/></ErRelationship><mxGeometry x="1103" y="853" width="100" height="50" as="geometry"/></mxCell><mxCell id="361" style="relationshipConnector" edge="1" parent="1" source="360" target="210"><ErRelationshipConnector cardinalityMin="0" cardinalityMax="N" as="value"><ErRelationshipConnectorGBHandler as="erGraphBehaviourHandler"/></ErRelationshipConnector><mxGeometry relative="1" as="geometry"><Array as="points"><mxPoint x="940" y="877"/></Array></mxGeometry></mxCell><mxCell id="362" style="relationshipConnector" edge="1" parent="1" source="360" target="210"><ErRelationshipConnector cardinalityMin="0" cardinalityMax="N" as="value"><ErRelationshipConnectorGBHandler as="erGraphBehaviourHandler"/></ErRelationshipConnector><mxGeometry relative="1" as="geometry"><Array as="points"><mxPoint x="1154" y="842"/></Array></mxGeometry></mxCell><mxCell id="363" style="entity" vertex="1" connectable="0" parent="1"><ErEntity name="Operace" as="value"><ErEntityGBHandler as="erGraphBehaviourHandler"/></ErEntity><mxGeometry x="336.71" y="648.82" width="100" height="40" as="geometry"/></mxCell><mxCell id="364" style="attribute;attributeLabelTop" vertex="1" connectable="0" parent="1"><ErAttribute name="cas" as="value"><ErAttributeGBHandler as="erGraphBehaviourHandler"/></ErAttribute><mxGeometry x="314" y="610" width="13" height="13" as="geometry"/></mxCell><mxCell id="365" style="attributeConnector" edge="1" parent="1" source="364" target="363"><ErAttributeConnector as="value"><ErAttributeConnectorGBHandler as="erGraphBehaviourHandler"/></ErAttributeConnector><mxGeometry relative="1" as="geometry"/></mxCell><mxCell id="366" style="relationship" vertex="1" parent="1"><ErRelationship name="pristupuje" as="value"><ErRelationshipGBHandler as="erGraphBehaviourHandler"/></ErRelationship><mxGeometry x="322.26" y="411.5" width="100" height="50" as="geometry"/></mxCell><mxCell id="367" style="relationshipConnector" edge="1" parent="1" source="366" target="108"><ErRelationshipConnector cardinalityMin="0" cardinalityMax="N" as="value"><ErRelationshipConnectorGBHandler as="erGraphBehaviourHandler"/></ErRelationshipConnector><mxGeometry relative="1" as="geometry"><Array as="points"><mxPoint x="371" y="293"/><mxPoint x="371" y="293"/></Array></mxGeometry></mxCell><mxCell id="368" style="relationshipConnector" edge="1" parent="1" source="366" target="363"><ErRelationshipConnector cardinalityMin="1" cardinalityMax="1" as="value"><ErRelationshipConnectorGBHandler as="erGraphBehaviourHandler"/></ErRelationshipConnector><mxGeometry relative="1" as="geometry"><Array as="points"><mxPoint x="373" y="597"/><mxPoint x="373" y="597"/></Array></mxGeometry></mxCell><mxCell id="369" style="relationship" vertex="1" parent="1"><ErRelationship name="provadi" as="value"><ErRelationshipGBHandler as="erGraphBehaviourHandler"/></ErRelationship><mxGeometry x="566" y="644.1" width="100" height="50" as="geometry"/></mxCell><mxCell id="370" style="relationshipConnector" edge="1" parent="1" source="369" target="210"><ErRelationshipConnector cardinalityMin="0" cardinalityMax="N" as="value"><ErRelationshipConnectorGBHandler as="erGraphBehaviourHandler"/></ErRelationshipConnector><mxGeometry relative="1" as="geometry"><Array as="points"><mxPoint x="615" y="709"/><mxPoint x="936" y="709"/></Array></mxGeometry></mxCell><mxCell id="371" style="relationshipConnector" edge="1" parent="1" source="369" target="363"><ErRelationshipConnector cardinalityMin="1" cardinalityMax="1" as="value"><ErRelationshipConnectorGBHandler as="erGraphBehaviourHandler"/></ErRelationshipConnector><mxGeometry relative="1" as="geometry"><Array as="points"><mxPoint x="534" y="669"/><mxPoint x="534" y="669"/></Array></mxGeometry></mxCell><mxCell id="372" style="relationship" vertex="1" parent="1"><ErRelationship name="kontroluje" as="value"><ErRelationshipGBHandler as="erGraphBehaviourHandler"/></ErRelationship><mxGeometry x="336.75" y="811" width="100" height="50" as="geometry"/></mxCell><mxCell id="373" style="relationshipConnector" edge="1" parent="1" source="372" target="363"><ErRelationshipConnector cardinalityMin="1" cardinalityMax="1" as="value"><ErRelationshipConnectorGBHandler as="erGraphBehaviourHandler"/></ErRelationshipConnector><mxGeometry relative="1" as="geometry"/></mxCell><mxCell id="374" style="relationshipConnector" edge="1" parent="1" source="372" target="209"><ErRelationshipConnector cardinalityMin="0" cardinalityMax="N" as="value"><ErRelationshipConnectorGBHandler as="erGraphBehaviourHandler"/></ErRelationshipConnector><mxGeometry relative="1" as="geometry"/></mxCell><mxCell id="375" style="compositeIdentifier" vertex="1" connectable="0" parent="1"><ErCompositeIdentifier as="value"><ErCompositeIdentifierGBHandler as="erGraphBehaviourHandler"/></ErCompositeIdentifier><mxGeometry as="geometry"><mxPoint x="323.3608477479653" y="630.5710596942046" as="sourcePoint"/><mxPoint x="454.9589403057956" y="684.0998999317404" as="targetPoint"/><Array as="points"><mxPoint x="338.3608477479653" y="630.5710596942046"/><mxPoint x="436.71" y="630.5710596942046"/><mxPoint x="454.95894030579547" y="630.5710596942046"/><mxPoint x="454.95894030579547" y="648.82"/><mxPoint x="454.9589403057955" y="669.0998999317404"/></Array></mxGeometry></mxCell><mxCell id="376" edge="1" parent="1" source="375" target="363" visible="0"><ErCompositeIdentifierConnector as="value"><ErCompositeIdentifierConnectorGBHandler as="erGraphBehaviourHandler"/></ErCompositeIdentifierConnector><mxGeometry relative="1" as="geometry"/></mxCell><mxCell id="377" edge="1" parent="1" source="375" target="365" visible="0"><ErCompositeIdentifierMember as="value"><ErCompositeIdentifierMemberGBHandler as="erGraphBehaviourHandler"/></ErCompositeIdentifierMember><mxGeometry relative="1" as="geometry"/></mxCell><mxCell id="378" style="intersectionPoint" vertex="1" connectable="0" parent="1"><ErCompositeIdentifierIntersectionPoint as="value"><ErCompositeIdentifierIPointGBHandler as="erGraphBehaviourHandler"/></ErCompositeIdentifierIntersectionPoint><mxGeometry x="336.3608477479653" y="628.5710596942046" width="4" height="4" as="geometry"/></mxCell><mxCell id="379" edge="1" parent="1" source="375" target="378" visible="0"><ErCompositeIdentifierIntersectionPointConnector as="value"><ErCompositeIdentifierIPointConnectorGBHandler as="erGraphBehaviourHandler"/></ErCompositeIdentifierIntersectionPointConnector><mxGeometry relative="1" as="geometry"/></mxCell><mxCell id="380" edge="1" parent="1" source="375" target="371" visible="0"><ErCompositeIdentifierMember as="value"><ErCompositeIdentifierMemberGBHandler as="erGraphBehaviourHandler"/></ErCompositeIdentifierMember><mxGeometry relative="1" as="geometry"/></mxCell><mxCell id="381" style="intersectionPoint" vertex="1" connectable="0" parent="1"><ErCompositeIdentifierIntersectionPoint as="value"><ErCompositeIdentifierIPointGBHandler as="erGraphBehaviourHandler"/></ErCompositeIdentifierIntersectionPoint><mxGeometry x="452.9589403057955" y="667.0998999317404" width="4" height="4" as="geometry"/></mxCell><mxCell id="382" edge="1" parent="1" source="375" target="381" visible="0"><ErCompositeIdentifierIntersectionPointConnector as="value"><ErCompositeIdentifierIPointConnectorGBHandler as="erGraphBehaviourHandler"/></ErCompositeIdentifierIntersectionPointConnector><mxGeometry relative="1" as="geometry"/></mxCell><mxCell id="383" style="compositeIdentifier" vertex="1" connectable="0" parent="1"><ErCompositeIdentifier as="value"><ErCompositeIdentifierGBHandler as="erGraphBehaviourHandler"/></ErCompositeIdentifier><mxGeometry as="geometry"><mxPoint x="401.74758724071467" y="710.1104303567615" as="sourcePoint"/><mxPoint x="349.51620618740117" y="627.5295696432385" as="targetPoint"/><Array as="points"><mxPoint x="386.74758724071467" y="710.1104303567615"/><mxPoint x="336.71" y="710.1104303567614"/><mxPoint x="315.41956964323856" y="710.1104303567614"/><mxPoint x="315.41956964323856" y="688.82"/><mxPoint x="315.41956964323856" y="648.82"/><mxPoint x="315.41956964323856" y="627.5295696432387"/><mxPoint x="334.51620618740117" y="627.5295696432386"/></Array></mxGeometry></mxCell><mxCell id="384" edge="1" parent="1" source="383" target="363" visible="0"><ErCompositeIdentifierConnector as="value"><ErCompositeIdentifierConnectorGBHandler as="erGraphBehaviourHandler"/></ErCompositeIdentifierConnector><mxGeometry relative="1" as="geometry"/></mxCell><mxCell id="385" edge="1" parent="1" source="383" target="373" visible="0"><ErCompositeIdentifierMember as="value"><ErCompositeIdentifierMemberGBHandler as="erGraphBehaviourHandler"/></ErCompositeIdentifierMember><mxGeometry relative="1" as="geometry"/></mxCell><mxCell id="386" style="intersectionPoint" vertex="1" connectable="0" parent="1"><ErCompositeIdentifierIntersectionPoint as="value"><ErCompositeIdentifierIPointGBHandler as="erGraphBehaviourHandler"/></ErCompositeIdentifierIntersectionPoint><mxGeometry x="384.74758724071467" y="708.1104303567615" width="4" height="4" as="geometry"/></mxCell><mxCell id="387" edge="1" parent="1" source="383" target="386" visible="0"><ErCompositeIdentifierIntersectionPointConnector as="value"><ErCompositeIdentifierIPointConnectorGBHandler as="erGraphBehaviourHandler"/></ErCompositeIdentifierIntersectionPointConnector><mxGeometry relative="1" as="geometry"/></mxCell><mxCell id="388" edge="1" parent="1" source="383" target="365" visible="0"><ErCompositeIdentifierMember as="value"><ErCompositeIdentifierMemberGBHandler as="erGraphBehaviourHandler"/></ErCompositeIdentifierMember><mxGeometry relative="1" as="geometry"/></mxCell><mxCell id="389" style="intersectionPoint" vertex="1" connectable="0" parent="1"><ErCompositeIdentifierIntersectionPoint as="value"><ErCompositeIdentifierIPointGBHandler as="erGraphBehaviourHandler"/></ErCompositeIdentifierIntersectionPoint><mxGeometry x="332.51620618740117" y="625.5295696432386" width="4" height="4" as="geometry"/></mxCell><mxCell id="390" edge="1" parent="1" source="383" target="389" visible="0"><ErCompositeIdentifierIntersectionPointConnector as="value"><ErCompositeIdentifierIPointConnectorGBHandler as="erGraphBehaviourHandler"/></ErCompositeIdentifierIntersectionPointConnector><mxGeometry relative="1" as="geometry"/></mxCell><mxCell id="391" style="compositeIdentifier" vertex="1" connectable="0" parent="1"><ErCompositeIdentifier as="value"><ErCompositeIdentifierGBHandler as="erGraphBehaviourHandler"/></ErCompositeIdentifier><mxGeometry as="geometry"><mxPoint x="327.20548930852954" y="633.6125497451704" as="sourcePoint"/><mxPoint x="387.264828620025" y="633.6125497451704" as="targetPoint"/><Array as="points"><mxPoint x="342.20548930852954" y="633.6125497451704"/><mxPoint x="372.264828620025" y="633.6125497451704"/></Array></mxGeometry></mxCell><mxCell id="392" edge="1" parent="1" source="391" target="363" visible="0"><ErCompositeIdentifierConnector as="value"><ErCompositeIdentifierConnectorGBHandler as="erGraphBehaviourHandler"/></ErCompositeIdentifierConnector><mxGeometry relative="1" as="geometry"/></mxCell><mxCell id="393" edge="1" parent="1" source="391" target="365" visible="0"><ErCompositeIdentifierMember as="value"><ErCompositeIdentifierMemberGBHandler as="erGraphBehaviourHandler"/></ErCompositeIdentifierMember><mxGeometry relative="1" as="geometry"/></mxCell><mxCell id="394" style="intersectionPoint" vertex="1" connectable="0" parent="1"><ErCompositeIdentifierIntersectionPoint as="value"><ErCompositeIdentifierIPointGBHandler as="erGraphBehaviourHandler"/></ErCompositeIdentifierIntersectionPoint><mxGeometry x="340.20548930852954" y="631.6125497451704" width="4" height="4" as="geometry"/></mxCell><mxCell id="395" edge="1" parent="1" source="391" target="394" visible="0"><ErCompositeIdentifierIntersectionPointConnector as="value"><ErCompositeIdentifierIPointConnectorGBHandler as="erGraphBehaviourHandler"/></ErCompositeIdentifierIntersectionPointConnector><mxGeometry relative="1" as="geometry"/></mxCell><mxCell id="396" edge="1" parent="1" source="391" target="368" visible="0"><ErCompositeIdentifierMember as="value"><ErCompositeIdentifierMemberGBHandler as="erGraphBehaviourHandler"/></ErCompositeIdentifierMember><mxGeometry relative="1" as="geometry"/></mxCell><mxCell id="397" style="intersectionPoint" vertex="1" connectable="0" parent="1"><ErCompositeIdentifierIntersectionPoint as="value"><ErCompositeIdentifierIPointGBHandler as="erGraphBehaviourHandler"/></ErCompositeIdentifierIntersectionPoint><mxGeometry x="370.264828620025" y="631.6125497451704" width="4" height="4" as="geometry"/></mxCell><mxCell id="398" edge="1" parent="1" source="391" target="397" visible="0"><ErCompositeIdentifierIntersectionPointConnector as="value"><ErCompositeIdentifierIPointConnectorGBHandler as="erGraphBehaviourHandler"/></ErCompositeIdentifierIntersectionPointConnector><mxGeometry relative="1" as="geometry"/></mxCell><mxCell id="401" style="entity" vertex="1" connectable="0" parent="1"><ErEntity name="Vypujcka" as="value"><ErEntityGBHandler as="erGraphBehaviourHandler"/></ErEntity><mxGeometry x="-39" y="768.3" width="100" height="40" as="geometry"/></mxCell><mxCell id="402" style="entity" vertex="1" connectable="0" parent="1"><ErEntity name="Vraceni" as="value"><ErEntityGBHandler as="erGraphBehaviourHandler"/></ErEntity><mxGeometry x="122" y="768.3" width="100" height="40" as="geometry"/></mxCell><mxCell id="403" style="hierarchy" vertex="1" connectable="0" parent="1"><ErHierarchy coverage="Complete" disjointness="Exclusive" as="value"><ErHierarchyGBHandler as="erGraphBehaviourHandler"/></ErHierarchy><mxGeometry x="76.69164614843334" y="705.9760075905522" width="10" height="10" as="geometry"/></mxCell><mxCell id="404" style="generalization" edge="1" parent="1" source="403" target="363"><ErGeneralizationConnector as="value"><ErGeneralizationConnectorGBHandler as="erGraphBehaviourHandler"/></ErGeneralizationConnector><mxGeometry relative="1" as="geometry"><Array as="points"><mxPoint x="82" y="668"/></Array></mxGeometry></mxCell><mxCell id="405" style="specialization" edge="1" parent="1" source="403" target="401"><ErSpecializationConnector as="value"><ErSpecializationConnectorGBHandler as="erGraphBehaviourHandler"/></ErSpecializationConnector><mxGeometry relative="1" as="geometry"/></mxCell><mxCell id="406" style="specialization" edge="1" parent="1" source="403" target="402"><ErSpecializationConnector as="value"><ErSpecializationConnectorGBHandler as="erGraphBehaviourHandler"/></ErSpecializationConnector><mxGeometry relative="1" as="geometry"/></mxCell><mxCell id="407" style="attribute;attributeLabelBottom" vertex="1" connectable="0" parent="1"><ErAttribute name="datum" as="value"><ErAttributeGBHandler as="erGraphBehaviourHandler"/></ErAttribute><mxGeometry x="-40" y="833.3" width="13" height="13" as="geometry"/></mxCell><mxCell id="408" style="attributeConnector" edge="1" parent="1" source="407" target="401"><ErAttributeConnector as="value"><ErAttributeConnectorGBHandler as="erGraphBehaviourHandler"/></ErAttributeConnector><mxGeometry relative="1" as="geometry"/></mxCell><mxCell id="409" style="attribute;attributeLabelTop" vertex="1" connectable="0" parent="1"><ErAttribute name="stav" as="value"><ErAttributeGBHandler as="erGraphBehaviourHandler"/></ErAttribute><mxGeometry x="246" y="779.3" width="13" height="13" as="geometry"/></mxCell><mxCell id="410" style="attributeConnector" edge="1" parent="1" source="409" target="402"><ErAttributeConnector as="value"><ErAttributeConnectorGBHandler as="erGraphBehaviourHandler"/></ErAttributeConnector><mxGeometry relative="1" as="geometry"/></mxCell><mxCell id="411" style="attribute;attributeLabelBottom" vertex="1" connectable="0" parent="1"><ErAttribute name="cena" as="value"><ErAttributeGBHandler as="erGraphBehaviourHandler"/></ErAttribute><mxGeometry y="835.3" width="13" height="13" as="geometry"/></mxCell><mxCell id="412" style="attributeConnector" edge="1" parent="1" source="411" target="401"><ErAttributeConnector as="value"><ErAttributeConnectorGBHandler as="erGraphBehaviourHandler"/></ErAttributeConnector><mxGeometry relative="1" as="geometry"/></mxCell><mxCell id="413" style="attribute;attributeLabelBottom" vertex="1" connectable="0" parent="1"><ErAttribute name="pokuta" as="value"><ErAttributeGBHandler as="erGraphBehaviourHandler"/></ErAttribute><mxGeometry x="48" y="833.3" width="13" height="13" as="geometry"/></mxCell><mxCell id="414" style="attributeConnector" edge="1" parent="1" source="413" target="401"><ErAttributeConnector as="value"><ErAttributeConnectorGBHandler as="erGraphBehaviourHandler"/></ErAttributeConnector><mxGeometry relative="1" as="geometry"/></mxCell></root></mxGraphModel>